{"title":"R Jogi - Basic Ophthalmology, 4th Edition.pdf","uid":9786028,"size":20595333,"categoryP":"other","categoryS":"e_books","magnet":"?xt=urn:btih:0188d122c3d4d8067f2355c723191972bab360e3&amp;dn=R+Jogi+-+Basic+Ophthalmology%2C+4th+Edition.pdf&amp;tr=udp%3A%2F%2Ftracker.openbittorrent.com%3A80&amp;tr=udp%3A%2F%2Fopen.demonii.com%3A1337&amp;tr=udp%3A%2F%2Ftracker.coppersurfer.tk%3A6969&amp;tr=udp%3A%2F%2Fexodus.desync.com%3A6969","seeders":6,"leechers":0,"uploader":"vickey1992","files":1,"time":1395161464,"description":"This book deals with the basic concepts, fundamentals and recent advances in Opthalmology - It provides guidance on the latest diagnostic approach, operative techniques and treatment options - This comprehensive, authoritative and richly illustrated textbook covers basic and clinical principles in Opthalmology to ensure that students will always be able t find the guidance they need to diagnose and manage patient's ocular problems and also match with the best standards of care - This book discusses traditional and conventional course of visual disorders and explores new contemporary causes generated by modern urban lifestyles like visual display terminal syndrome caused by computer monitor and use of contact lenses. Also covers easy treatment of diabetic retinopathy study for visual rehabilitation\n\nThis book deals with the basic concepts, fundamentals and recent advances in Opthalmology It provides guidance on the latest diagnostic approach, operative techniques and treatment options This comprehensive, authoritative and richly illustrated textbook covers basic and clinical principles in Opthalmology to ensure that students will always be able t find the guidance they need to diagnose and manage patient's ocular problems and also match with the best standards of care This book discusses traditional and conventional course of visual disorders and explores new contemporary causes generated by modern urban lifestyles like visual display terminal syndrome caused by computer monitor and use of contact lenses. Also covers easy treatment of diabetic retinopathy study for visual rehabilitation\n\n\nCopyright to the respective owners.If you like this book then please buy it.\nSharing is caring,Seed this torrent so others could enjoy it too.\nAny requests/suggestions can be made in the comments section or via email to &lt;a class=&quot;__cf_email__&quot; href=&quot;/cdn-cgi/l/email-protection&quot; data-cfemail=&quot;bfd2cad7ded2d2dedb91c8decedecd91dedddddeccffd3d6c9da91dcd0d2&quot;&gt;[email&amp;#160;protected]&lt;/a&gt;&lt;script cf-hash='f9e31' type=&quot;text/javascript&quot;&gt;\n/* &lt;![CDATA[ */!function(){try{var t=&quot;currentScript&quot;in document?document.currentScript:function(){for(var t=document.getElementsByTagName(&quot;script&quot;),e=t.length;e--;)if(t[e].getAttribute(&quot;cf-hash&quot;))return t[e]}();if(t&amp;&amp;t.previousSibling){var e,r,n,i,c=t.previousSibling,a=c.getAttribute(&quot;data-cfemail&quot;);if(a){for(e=&quot;&quot;,r=parseInt(a.substr(0,2),16),n=2;a.length-n;n+=2)i=parseInt(a.substr(n,2),16)^r,e+=String.fromCharCode(i);e=document.createTextNode(e),c.parentNode.replaceChild(e,c)}}}catch(u){}}();/* ]]&gt; */&lt;/script&gt;\nThanks","torrent":{"xt":"urn:btih:0188d122c3d4d8067f2355c723191972bab360e3","amp;dn":"R+Jogi+-+Basic+Ophthalmology%2C+4th+Edition.pdf","amp;tr":["udp%3A%2F%2Ftracker.openbittorrent.com%3A80","udp%3A%2F%2Fopen.demonii.com%3A1337","udp%3A%2F%2Ftracker.coppersurfer.tk%3A6969","udp%3A%2F%2Fexodus.desync.com%3A6969"],"infoHash":"0188d122c3d4d8067f2355c723191972bab360e3","infoHashBuffer":{"type":"Buffer","data":[1,136,209,34,195,212,216,6,127,35,85,199,35,25,25,114,186,179,96,227]},"announce":[],"urlList":[]}}