{"title":"DmC: Devil May Cry 2013 - NoDVD - Crack","uid":8066901,"size":150701,"categoryP":"games","categoryS":"pc","magnet":"?xt=urn:btih:128177fc167bb668ff224cc1d8961defd4571c41&amp;dn=DmC%3A+Devil+May+Cry+2013+-+NoDVD+-+Crack&amp;tr=udp%3A%2F%2Ftracker.openbittorrent.com%3A80&amp;tr=udp%3A%2F%2Fopen.demonii.com%3A1337&amp;tr=udp%3A%2F%2Ftracker.coppersurfer.tk%3A6969&amp;tr=udp%3A%2F%2Fexodus.desync.com%3A6969","seeders":6,"leechers":0,"uploader":"soulking77","files":2,"time":1359199248,"description":"                      DmC: Devil May Cry 5 2013 - NoDVD - Crack\n\nSystem Requirements\nCPU: \tAMD Phenomâ„¢ II X4 3 Ghz or better, IntelÂ® Coreâ„¢2 Quad 2.7 Ghz or better\nRAM: \t4 GB RAM\nVGA: \tAMD Radeonâ„¢ HD 6950 or better\nDX: \t9.0c or greater\nOS: \tWindows VistaÂ®/XP, Windows 7, Windows 8\nHDD: \t9 GB free hard drive space\nSound: \tStandard audio device\n\n\nRelease year: 2013\nGenre: Action, Slasher, 3D, 3rd, Person\nDeveloper: Ninja Theory\nPublisher: Capcom\nRelease Group / Person: RELOADED Installation:\n\nInstallation:\n1. Unrar.\n2. Burn or mount the image.\n3. Install the game.\n4. Copy the content from /crack directory on the DVD to the Win32\ndirectory of the game, overwriting the existing file.\n5. Play the game.\n6. Support the software developers. If you like this game, BUY IT!\n\ninstallation Crack:\n1) Install the game.\n2) Copy all the contents of the Crack into the installed game Win32.\n3) Play.","torrent":{"xt":"urn:btih:128177fc167bb668ff224cc1d8961defd4571c41","amp;dn":"DmC%3A+Devil+May+Cry+2013+-+NoDVD+-+Crack","amp;tr":["udp%3A%2F%2Ftracker.openbittorrent.com%3A80","udp%3A%2F%2Fopen.demonii.com%3A1337","udp%3A%2F%2Ftracker.coppersurfer.tk%3A6969","udp%3A%2F%2Fexodus.desync.com%3A6969"],"infoHash":"128177fc167bb668ff224cc1d8961defd4571c41","infoHashBuffer":{"type":"Buffer","data":[18,129,119,252,22,123,182,104,255,34,76,193,216,150,29,239,212,87,28,65]},"announce":[],"urlList":[]}}