{"title":"[SexArt] Ivana Sugar - Out Of Plans (22.05.2016)","uid":14673770,"size":235385366,"categoryP":"porn","categoryS":"movie_clips","magnet":"?xt=urn:btih:140c0725a31fb20ad3508e2fc75d63a3f0052a4a&amp;dn=%5BSexArt%5D+Ivana+Sugar+-+Out+Of+Plans+%2822.05.2016%29&amp;tr=udp%3A%2F%2Ftracker.leechers-paradise.org%3A6969&amp;tr=udp%3A%2F%2Fzer0day.ch%3A1337&amp;tr=udp%3A%2F%2Fopen.demonii.com%3A1337&amp;tr=udp%3A%2F%2Ftracker.coppersurfer.tk%3A6969&amp;tr=udp%3A%2F%2Fexodus.desync.com%3A6969","seeders":6,"leechers":0,"uploader":"KayWily","files":1,"time":1463908843,"description":"[SexArt] Ivana Sugar - Out Of Plans (22.05.2016)\r\n\r\n \nhttp://porn-harbor.com/image/NjN","torrent":{"xt":"urn:btih:140c0725a31fb20ad3508e2fc75d63a3f0052a4a","amp;dn":"%5BSexArt%5D+Ivana+Sugar+-+Out+Of+Plans+%2822.05.2016%29","amp;tr":["udp%3A%2F%2Ftracker.leechers-paradise.org%3A6969","udp%3A%2F%2Fzer0day.ch%3A1337","udp%3A%2F%2Fopen.demonii.com%3A1337","udp%3A%2F%2Ftracker.coppersurfer.tk%3A6969","udp%3A%2F%2Fexodus.desync.com%3A6969"],"infoHash":"140c0725a31fb20ad3508e2fc75d63a3f0052a4a","infoHashBuffer":{"type":"Buffer","data":[20,12,7,37,163,31,178,10,211,80,142,47,199,93,99,163,240,5,42,74]},"announce":[],"urlList":[]}}