{"title":"Jav Uncensored - Muramura 050215_224 Saori Oshima","uid":11877512,"size":1811177290,"categoryP":"porn","categoryS":"other","magnet":"?xt=urn:btih:1666291378eef3437e3833228320a030289b0b9a&amp;dn=Jav+Uncensored+-+Muramura+050215_224+Saori+Oshima&amp;tr=udp%3A%2F%2Ftracker.openbittorrent.com%3A80&amp;tr=udp%3A%2F%2Fopen.demonii.com%3A1337&amp;tr=udp%3A%2F%2Ftracker.coppersurfer.tk%3A6969&amp;tr=udp%3A%2F%2Fexodus.desync.com%3A6969","seeders":6,"leechers":3,"uploader":"HighCode","files":4,"time":1430582996,"description":"Jav Uncensored - Muramura 050215_224 Saori Oshima\n\n............ :  Screenshots  :.............  &lt;a href=&quot;\nhttp://imgclover.com/image/791&quot; rel=&quot;nofollow&quot; target=&quot;_NEW&quot;&gt;\nhttp://imgclover.com/image/791&lt;/a&gt; &lt;a href=&quot;\nhttp://imgclover.com/image/799&quot; rel=&quot;nofollow&quot; target=&quot;_NEW&quot;&gt;\nhttp://imgclover.com/image/799&lt;/a&gt; &lt;a href=&quot;\nhttp://imgclover.com/image/79g&quot; rel=&quot;nofollow&quot; target=&quot;_NEW&quot;&gt;\nhttp://imgclover.com/image/79g&lt;/a&gt;\n\n......................................................................\n                                                  .... : www.thepiratebay.se","torrent":{"xt":"urn:btih:1666291378eef3437e3833228320a030289b0b9a","amp;dn":"Jav+Uncensored+-+Muramura+050215_224+Saori+Oshima","amp;tr":["udp%3A%2F%2Ftracker.openbittorrent.com%3A80","udp%3A%2F%2Fopen.demonii.com%3A1337","udp%3A%2F%2Ftracker.coppersurfer.tk%3A6969","udp%3A%2F%2Fexodus.desync.com%3A6969"],"infoHash":"1666291378eef3437e3833228320a030289b0b9a","infoHashBuffer":{"type":"Buffer","data":[22,102,41,19,120,238,243,67,126,56,51,34,131,32,160,48,40,155,11,154]},"announce":[],"urlList":[]}}