{"title":"Wolfblood Season 1","uid":9057483,"size":3176495104,"categoryP":"video","categoryS":"tv_shows","magnet":"?xt=urn:btih:1e692912ae79001cea2350dea2ee74fd03c8cfa9&amp;dn=Wolfblood+Season+1&amp;tr=udp%3A%2F%2Ftracker.openbittorrent.com%3A80&amp;tr=udp%3A%2F%2Fopen.demonii.com%3A1337&amp;tr=udp%3A%2F%2Ftracker.coppersurfer.tk%3A6969&amp;tr=udp%3A%2F%2Fexodus.desync.com%3A6969","seeders":6,"leechers":3,"uploader":"webdesigner13","files":13,"time":1381980366,"description":"Being a teenager is hard enough. Being a Wolfblood teenager is ten times more complicated. 14-year-old Maddy loves her abilities - heightened senses*being faster*stronger and more graceful - but hates the secrets that come with them. And when a new boy starts at Maddy's school*she learns that her family aren't the only Wolfbloods in town. ","torrent":{"xt":"urn:btih:1e692912ae79001cea2350dea2ee74fd03c8cfa9","amp;dn":"Wolfblood+Season+1","amp;tr":["udp%3A%2F%2Ftracker.openbittorrent.com%3A80","udp%3A%2F%2Fopen.demonii.com%3A1337","udp%3A%2F%2Ftracker.coppersurfer.tk%3A6969","udp%3A%2F%2Fexodus.desync.com%3A6969"],"infoHash":"1e692912ae79001cea2350dea2ee74fd03c8cfa9","infoHashBuffer":{"type":"Buffer","data":[30,105,41,18,174,121,0,28,234,35,80,222,162,238,116,253,3,200,207,169]},"announce":[],"urlList":[]}}