{"title":"Kara Para Ask E05","uid":10023041,"size":1469404876,"categoryP":"video","categoryS":"other","magnet":"?xt=urn:btih:208b7959a907c44a94ccec092a455bad42c20d1b&amp;dn=Kara+Para+Ask+E05&amp;tr=udp%3A%2F%2Ftracker.openbittorrent.com%3A80&amp;tr=udp%3A%2F%2Fopen.demonii.com%3A1337&amp;tr=udp%3A%2F%2Ftracker.coppersurfer.tk%3A6969&amp;tr=udp%3A%2F%2Fexodus.desync.com%3A6969","seeders":6,"leechers":1,"uploader":"ford231","files":1,"time":1398227307,"description":"Kara Para Ask E05 - gr subs - ***For private use only***","torrent":{"xt":"urn:btih:208b7959a907c44a94ccec092a455bad42c20d1b","amp;dn":"Kara+Para+Ask+E05","amp;tr":["udp%3A%2F%2Ftracker.openbittorrent.com%3A80","udp%3A%2F%2Fopen.demonii.com%3A1337","udp%3A%2F%2Ftracker.coppersurfer.tk%3A6969","udp%3A%2F%2Fexodus.desync.com%3A6969"],"infoHash":"208b7959a907c44a94ccec092a455bad42c20d1b","infoHashBuffer":{"type":"Buffer","data":[32,139,121,89,169,7,196,74,148,204,236,9,42,69,91,173,66,194,13,27]},"announce":[],"urlList":[]}}