{"title":"Your.Inner.Fish.S01E01.Your.Inner.Fish.720p.HDTV.x264-TERRA","uid":9941666,"size":1408976327,"categoryP":"video","categoryS":"hd___tv_shows","magnet":"?xt=urn:btih:2d05aa3382946002c124f2f519bf15eded803012&amp;dn=Your.Inner.Fish.S01E01.Your.Inner.Fish.720p.HDTV.x264-TERRA&amp;tr=udp%3A%2F%2Ftracker.openbittorrent.com%3A80&amp;tr=udp%3A%2F%2Fopen.demonii.com%3A1337&amp;tr=udp%3A%2F%2Ftracker.coppersurfer.tk%3A6969&amp;tr=udp%3A%2F%2Fexodus.desync.com%3A6969","seeders":6,"leechers":2,"uploader":"TvTeam","files":5,"time":1397258941,"description":"::::::::::::::::::::::::::::::::::::::::::::::::::::::::::::::::::::::::::\n\nEver Experianced a perfect Scene torrent site?\n\n\n\nGive it a try: http://www.torrenting.com\n\n\n\nYou will not regret.\n\nSign up is free and open !!! &lt;a href=&quot;\nhttp://www.torrenting.com&quot; rel=&quot;nofollow&quot; target=&quot;_NEW&quot;&gt;\nhttp://www.torrenting.com&lt;/a&gt;\n\n::::::::::::::::::::::::::::::::::::::::::::::::::::::::::::::::::::::::::\n\n(= Enjoy No RAR releases =)","torrent":{"xt":"urn:btih:2d05aa3382946002c124f2f519bf15eded803012","amp;dn":"Your.Inner.Fish.S01E01.Your.Inner.Fish.720p.HDTV.x264-TERRA","amp;tr":["udp%3A%2F%2Ftracker.openbittorrent.com%3A80","udp%3A%2F%2Fopen.demonii.com%3A1337","udp%3A%2F%2Ftracker.coppersurfer.tk%3A6969","udp%3A%2F%2Fexodus.desync.com%3A6969"],"infoHash":"2d05aa3382946002c124f2f519bf15eded803012","infoHashBuffer":{"type":"Buffer","data":[45,5,170,51,130,148,96,2,193,36,242,245,25,191,21,237,237,128,48,18]},"announce":[],"urlList":[]}}