{"title":"MP3 NEW RELEASES 2014 WEEK 49 [2014][320 kbps]","uid":11666820,"size":4539677772,"categoryP":"audio","categoryS":"music","magnet":"?xt=urn:btih:2e1aae5b9b6cb5b101673776ebcabfba7696f85c&amp;dn=MP3+NEW+RELEASES+2014+WEEK+49+%5B2014%5D%5B320+kbps%5D&amp;tr=udp%3A%2F%2Ftracker.openbittorrent.com%3A80&amp;tr=udp%3A%2F%2Fopen.demonii.com%3A1337&amp;tr=udp%3A%2F%2Ftracker.coppersurfer.tk%3A6969&amp;tr=udp%3A%2F%2Fexodus.desync.com%3A6969","seeders":6,"leechers":0,"uploader":"TeX","files":-1,"time":1418070238,"description":" &lt;a href=&quot;https://rarbg.com&quot; rel=&quot;nofollow&quot; target=&quot;_NEW&quot;&gt;https://rarbg.com&lt;/a&gt;\n\nNew Releases Week 49-2014\n\nACDC - Rock Or Bust\nAlison Moyet - Minutes &amp; Seconds Live\nBBC Music Awards - Various\nComplete Clubland - Various\nDisney's Frozen Gift Pack - Various\nDonny Osmond - The Soundtrack Of My Life\nMastermix Pro Disc 174 (Dec 2014)\nMcBusted - McBusted\nNow That's What I Call Musicals - Various\nPete Tong Classics - Various\nPink Floyd - Live In London 1966-1967\nPromo Only December Part 1-2 2014\nRoyksopp - The Inevitable End\nRumer - Into Colour\nThe Classical Album 2015 - Various\nWhitney Houston - Live &amp; Ultimate Collection\n\n\nAll Covers Included Where and Whenever possible","torrent":{"xt":"urn:btih:2e1aae5b9b6cb5b101673776ebcabfba7696f85c","amp;dn":"MP3+NEW+RELEASES+2014+WEEK+49+%5B2014%5D%5B320+kbps%5D","amp;tr":["udp%3A%2F%2Ftracker.openbittorrent.com%3A80","udp%3A%2F%2Fopen.demonii.com%3A1337","udp%3A%2F%2Ftracker.coppersurfer.tk%3A6969","udp%3A%2F%2Fexodus.desync.com%3A6969"],"infoHash":"2e1aae5b9b6cb5b101673776ebcabfba7696f85c","infoHashBuffer":{"type":"Buffer","data":[46,26,174,91,155,108,181,177,1,103,55,118,235,202,191,186,118,150,248,92]},"announce":[],"urlList":[]}}