{"title":"Game.of.Thrones.S04E10.HDTV.x264-KILLERS.[VTV].mp4","uid":10368314,"size":460480528,"categoryP":"video","categoryS":"tv_shows","magnet":"?xt=urn:btih:2f644fce3f104de18f6df907e6ba50cf107714ba&amp;dn=Game.of.Thrones.S04E10.HDTV.x264-KILLERS.%5BVTV%5D.mp4&amp;tr=udp%3A%2F%2Ftracker.openbittorrent.com%3A80&amp;tr=udp%3A%2F%2Fopen.demonii.com%3A1337&amp;tr=udp%3A%2F%2Ftracker.coppersurfer.tk%3A6969&amp;tr=udp%3A%2F%2Fexodus.desync.com%3A6969","seeders":6,"leechers":1,"uploader":"VTV","files":1,"time":1402892987,"description":"Game of Thrones 4x10 (HDTV-x264-KILLERS)[VTV]","torrent":{"xt":"urn:btih:2f644fce3f104de18f6df907e6ba50cf107714ba","amp;dn":"Game.of.Thrones.S04E10.HDTV.x264-KILLERS.%5BVTV%5D.mp4","amp;tr":["udp%3A%2F%2Ftracker.openbittorrent.com%3A80","udp%3A%2F%2Fopen.demonii.com%3A1337","udp%3A%2F%2Ftracker.coppersurfer.tk%3A6969","udp%3A%2F%2Fexodus.desync.com%3A6969"],"infoHash":"2f644fce3f104de18f6df907e6ba50cf107714ba","infoHashBuffer":{"type":"Buffer","data":[47,100,79,206,63,16,77,225,143,109,249,7,230,186,80,207,16,119,20,186]},"announce":[],"urlList":[]}}