{"title":"Yeah Yeah Yeahs - Mosquito [Deluxe Edition] [2013]","uid":8351798,"size":150707957,"categoryP":"audio","categoryS":"other","magnet":"?xt=urn:btih:343941c33a2ec10de388703f63c0115c725abf97&amp;dn=Yeah+Yeah+Yeahs+-+Mosquito+%5BDeluxe+Edition%5D+%5B2013%5D&amp;tr=udp%3A%2F%2Ftracker.openbittorrent.com%3A80&amp;tr=udp%3A%2F%2Fopen.demonii.com%3A1337&amp;tr=udp%3A%2F%2Ftracker.coppersurfer.tk%3A6969&amp;tr=udp%3A%2F%2Fexodus.desync.com%3A6969","seeders":6,"leechers":1,"uploader":"V3nom","files":-1,"time":1365363260,"description":"[img]http://img594.imageshack.us/img594/17/yeahyeah.jpg[/img]\n\n[code]Yeah Yeah Yeahs - Mosquito [Deluxe Edition] [2013][/code]\n\n[code]Artist: Yeah Yeah Yeahs\nTitle Of Album: Mosquito\nYear Of Release: 2013\nLabel: Interscope Records\nGenre: Indie Rock\nQuality: MP3\nBitrate: CBR 320 kbps\nTotal Time: 01:02:41\nTotal Size: 143 Mb[/code]\n\n[code]Tracklist:\n\n01. Sacrilege\n02. Subway\n03. Mosquito\n04. Under The Earth\n05. Slave\n06. These Paths\n07. Area 52\n08. Buried Alive (ft. Dr. Octagon)\n09. Always\n10. Despair\n11. Wedding Song\n12. Subway (NOLA demo)\n13. Wedding Song (Acoustic)\n14. Despair (Acoustic)\n15. Mosquito (Live from YYY's Bunker Studio)[/code]\n[img]http://kastatic.com/i2/users/133df62bbf28e62494bb17fe11078f1a.gif[/img][img]http://kastatic.com/i2/users/133df62bbf28e62494bb17fe11078f1a.gif[/img]","torrent":{"xt":"urn:btih:343941c33a2ec10de388703f63c0115c725abf97","amp;dn":"Yeah+Yeah+Yeahs+-+Mosquito+%5BDeluxe+Edition%5D+%5B2013%5D","amp;tr":["udp%3A%2F%2Ftracker.openbittorrent.com%3A80","udp%3A%2F%2Fopen.demonii.com%3A1337","udp%3A%2F%2Ftracker.coppersurfer.tk%3A6969","udp%3A%2F%2Fexodus.desync.com%3A6969"],"infoHash":"343941c33a2ec10de388703f63c0115c725abf97","infoHashBuffer":{"type":"Buffer","data":[52,57,65,195,58,46,193,13,227,136,112,63,99,192,17,92,114,90,191,151]},"announce":[],"urlList":[]}}