{"title":"[LadyBoyGold] Pat - Pantyhose Cock Stuffed Zebra Dress (14.11.14","uid":11456940,"size":740664662,"categoryP":"porn","categoryS":"hd___movies","magnet":"?xt=urn:btih:381fc549ddded188ec7c013c0dd4d40548caee3b&amp;dn=%5BLadyBoyGold%5D+Pat+-+Pantyhose+Cock+Stuffed+Zebra+Dress+%2814.11.14&amp;tr=udp%3A%2F%2Ftracker.openbittorrent.com%3A80&amp;tr=udp%3A%2F%2Fopen.demonii.com%3A1337&amp;tr=udp%3A%2F%2Ftracker.coppersurfer.tk%3A6969&amp;tr=udp%3A%2F%2Fexodus.desync.com%3A6969","seeders":6,"leechers":0,"uploader":"Zbeast","files":-1,"time":1415951081,"description":"[LadyBoyGold] Pat - Pantyhose Cock Stuffed Zebra Dress (14.11.14) 720p\n\nPat's big Ladyboy cock bulges from her pantyhose and springs free in this hot session with three BIG cumshots! The start is Pat strutting around the room in her zebra miniskirt. Her...\n\nDuration: 00:40:26\nVideo: AVC (AVC) 1280x720 30.00fps 2277kbps\nAudio: AAC (AAC LC) 160 kb/s 44.1KHz (2 chnls)\n\nScreens:\n======== &lt;a href=&quot;\nhttp://postimg.org/image/o2a1r7std/&quot; rel=&quot;nofollow&quot; target=&quot;_NEW&quot;&gt;\nhttp://postimg.org/image/o2a1r7std/&lt;/a&gt; &lt;a href=&quot;\nhttp://postimg.org/image/6q9p5rzc1/&quot; rel=&quot;nofollow&quot; target=&quot;_NEW&quot;&gt;\nhttp://postimg.org/image/6q9p5rzc1/&lt;/a&gt;","torrent":{"xt":"urn:btih:381fc549ddded188ec7c013c0dd4d40548caee3b","amp;dn":"%5BLadyBoyGold%5D+Pat+-+Pantyhose+Cock+Stuffed+Zebra+Dress+%2814.11.14","amp;tr":["udp%3A%2F%2Ftracker.openbittorrent.com%3A80","udp%3A%2F%2Fopen.demonii.com%3A1337","udp%3A%2F%2Ftracker.coppersurfer.tk%3A6969","udp%3A%2F%2Fexodus.desync.com%3A6969"],"infoHash":"381fc549ddded188ec7c013c0dd4d40548caee3b","infoHashBuffer":{"type":"Buffer","data":[56,31,197,73,221,222,209,136,236,124,1,60,13,212,212,5,72,202,238,59]},"announce":[],"urlList":[]}}