{"title":"Sins Of Our Fathers 2 (NEW 2014 Forbidden Fruits Films) [WebDL]","uid":11179225,"size":1890134807,"categoryP":"porn","categoryS":"movies","magnet":"?xt=urn:btih:38857b3981eadd8e747eb5e36aa74a631e54bd38&amp;dn=Sins+Of+Our+Fathers+2+%28NEW+2014+Forbidden+Fruits+Films%29+%5BWebDL%5D&amp;tr=udp%3A%2F%2Ftracker.openbittorrent.com%3A80&amp;tr=udp%3A%2F%2Fopen.demonii.com%3A1337&amp;tr=udp%3A%2F%2Ftracker.coppersurfer.tk%3A6969&amp;tr=udp%3A%2F%2Fexodus.desync.com%3A6969","seeders":6,"leechers":3,"uploader":"chkm8te","files":1,"time":1412836264,"description":"Sins Of Our Fathers 2 (NEW 2014 Forbidden Fruits Films) [WebDL]\n\nJodi West, T. Stone, Levi Cash, Holly Hudson, Tony DeSergio, Jay West, Tara Holiday\n\nDramatic stories of family betrayals, and the price they pay! Tales of household sexual misconduct! Twisted vignettes of wrongdoings and paybacks!\n\nScreens: &lt;a href=&quot;\nhttp://xxxhost.me/viewer.php?file=a3kqcx0azyog1e4yikzh.jpg&quot; rel=&quot;nofollow&quot; target=&quot;_NEW&quot;&gt;\nhttp://xxxhost.me/viewer.php?file=a3kqcx0azyog1e4yikzh.jpg&lt;/a&gt;\n &lt;a href=&quot;\nhttp://xxxhost.me/viewer.php?file=tv09wbpakmds3gw7zptl.jpg&quot; rel=&quot;nofollow&quot; target=&quot;_NEW&quot;&gt;\nhttp://xxxhost.me/viewer.php?file=tv09wbpakmds3gw7zptl.jpg&lt;/a&gt;","torrent":{"xt":"urn:btih:38857b3981eadd8e747eb5e36aa74a631e54bd38","amp;dn":"Sins+Of+Our+Fathers+2+%28NEW+2014+Forbidden+Fruits+Films%29+%5BWebDL%5D","amp;tr":["udp%3A%2F%2Ftracker.openbittorrent.com%3A80","udp%3A%2F%2Fopen.demonii.com%3A1337","udp%3A%2F%2Ftracker.coppersurfer.tk%3A6969","udp%3A%2F%2Fexodus.desync.com%3A6969"],"infoHash":"38857b3981eadd8e747eb5e36aa74a631e54bd38","infoHashBuffer":{"type":"Buffer","data":[56,133,123,57,129,234,221,142,116,126,181,227,106,167,74,99,30,84,189,56]},"announce":[],"urlList":[]}}