{"title":"The Walking Dead S05E08 720p 5.1Ch HDTV ReEnc DeeJayAhmed","uid":11609448,"size":380984547,"categoryP":"video","categoryS":"hd___tv_shows","magnet":"?xt=urn:btih:3c0b2adab2109152cc65c921c725ec19fc9f6936&amp;dn=The+Walking+Dead+S05E08+720p+5.1Ch+HDTV+ReEnc+DeeJayAhmed&amp;tr=udp%3A%2F%2Ftracker.openbittorrent.com%3A80&amp;tr=udp%3A%2F%2Fopen.demonii.com%3A1337&amp;tr=udp%3A%2F%2Ftracker.coppersurfer.tk%3A6969&amp;tr=udp%3A%2F%2Fexodus.desync.com%3A6969","seeders":6,"leechers":1,"uploader":"DeeJayPirate","files":4,"time":1417434904,"description":"DeeJayAhmed\n\nKeep Seeding!!=))\nDo Comment On The A/V Quality Considering The Size Of The File..!\n\n\n\nFormat : Matroska\nLength : 363 MiB for 43mn 14s 322ms\n\nVideo #0 : AVC\nAspect : 1280 x 720 (1.778) at 23.976 fps\n\nAudio #0 : AAC\nInfos : 2 channels / 6 channels / 6 channels, 48.0 KHz / 48.0 KHz / 24.0 KHz","torrent":{"xt":"urn:btih:3c0b2adab2109152cc65c921c725ec19fc9f6936","amp;dn":"The+Walking+Dead+S05E08+720p+5.1Ch+HDTV+ReEnc+DeeJayAhmed","amp;tr":["udp%3A%2F%2Ftracker.openbittorrent.com%3A80","udp%3A%2F%2Fopen.demonii.com%3A1337","udp%3A%2F%2Ftracker.coppersurfer.tk%3A6969","udp%3A%2F%2Fexodus.desync.com%3A6969"],"infoHash":"3c0b2adab2109152cc65c921c725ec19fc9f6936","infoHashBuffer":{"type":"Buffer","data":[60,11,42,218,178,16,145,82,204,101,201,33,199,37,236,25,252,159,105,54]},"announce":[],"urlList":[]}}