{"title":"Wagner - Orchestral music - Philadelphia Orchestra,Thielemann","uid":15576680,"size":288489904,"categoryP":"audio","categoryS":"flac","magnet":"?xt=urn:btih:4c54af838d3f6bd061e4b5ee6a2e70f19402f049&amp;dn=Wagner+-+Orchestral+music+-+Philadelphia+Orchestra%2CThielemann&amp;tr=udp%3A%2F%2Ftracker.leechers-paradise.org%3A6969&amp;tr=udp%3A%2F%2Fzer0day.ch%3A1337&amp;tr=udp%3A%2F%2Fopen.demonii.com%3A1337&amp;tr=udp%3A%2F%2Ftracker.coppersurfer.tk%3A6969&amp;tr=udp%3A%2F%2Fexodus.desync.com%3A6969","seeders":6,"leechers":0,"uploader":"connor17","files":5,"time":1471345869,"description":"Wagner\r\n\r\nOrchestral music\r\n\r\nThe Philadelphia Orchestra\r\nChristian Thielemann\r\n \nhttp://i.imgur.com/vnHfRG5.jpg","torrent":{"xt":"urn:btih:4c54af838d3f6bd061e4b5ee6a2e70f19402f049","amp;dn":"Wagner+-+Orchestral+music+-+Philadelphia+Orchestra%2CThielemann","amp;tr":["udp%3A%2F%2Ftracker.leechers-paradise.org%3A6969","udp%3A%2F%2Fzer0day.ch%3A1337","udp%3A%2F%2Fopen.demonii.com%3A1337","udp%3A%2F%2Ftracker.coppersurfer.tk%3A6969","udp%3A%2F%2Fexodus.desync.com%3A6969"],"infoHash":"4c54af838d3f6bd061e4b5ee6a2e70f19402f049","infoHashBuffer":{"type":"Buffer","data":[76,84,175,131,141,63,107,208,97,228,181,238,106,46,112,241,148,2,240,73]},"announce":[],"urlList":[]}}