{"title":"American Pie 2 (2001)","uid":10708421,"size":729512267,"categoryP":"video","categoryS":"hd___movies","magnet":"?xt=urn:btih:573cd607f880e8127ddccbf280bfe3a810606b5e&amp;dn=American+Pie+2+%282001%29&amp;tr=udp%3A%2F%2Ftracker.openbittorrent.com%3A80&amp;tr=udp%3A%2F%2Fopen.demonii.com%3A1337&amp;tr=udp%3A%2F%2Ftracker.coppersurfer.tk%3A6969&amp;tr=udp%3A%2F%2Fexodus.desync.com%3A6969","seeders":6,"leechers":2,"uploader":"DarkinBlade","files":-1,"time":1407325449,"description":"American Pie 2 (2001) [720p]\n\n\n  &lt;a href=&quot;\nhttp://www.imdb.com/title/tt0252866/&quot; rel=&quot;nofollow&quot; target=&quot;_NEW&quot;&gt;\nhttp://www.imdb.com/title/tt0252866/&lt;/a&gt;\n\n\n   [FORMAT]:.......................[ Matroska\n   [YEAR]:.........................[ 2001\n   [GENRE]:........................[ Comedy | Romance\n   [FILE SIZE]:....................[ 700MiB\n   [NO OF CDs]:....................[ 1\n   [RESOLUTION]:...................[ 1280*694\n   [ASPECT RATIO]:.................[ 16:9\n   [FRAME RATE]:...................[ 23.976 fps\n   [LANGUAGE ]:....................[ English\n   [SUBTITLES]:....................[ English Muxed (Can Turn Off/On)\n   [RUNTIME]:......................[ 1h 45mn\n\n\n\nThe continuing bawdy adventures of a group of friends reuniting after their first year of college.\n\nThe whole gang are back and as close as ever. They decide to get even closer by spending the summer together at a beach house. They decide to hold the biggest party ever to be seen, even if the preparation doesn't always go to plan. Especially when Stifler, Finch and Jim become more close to each other than they ever want to be and when Jim mistakes super glue for lubricant.\n\n\n\nScreenshots:\n  &lt;a href=&quot;\nhttp://k.min.us/ij80e6.png&quot; rel=&quot;nofollow&quot; target=&quot;_NEW&quot;&gt;\nhttp://k.min.us/ij80e6.png&lt;/a&gt;\n  &lt;a href=&quot;\nhttp://k.min.us/ijCxjw.png&quot; rel=&quot;nofollow&quot; target=&quot;_NEW&quot;&gt;\nhttp://k.min.us/ijCxjw.png&lt;/a&gt;\n  &lt;a href=&quot;\nhttp://k.min.us/ijCkwC.png&quot; rel=&quot;nofollow&quot; target=&quot;_NEW&quot;&gt;\nhttp://k.min.us/ijCkwC.png&lt;/a&gt;\n\n\n\n\nEnjoy !","torrent":{"xt":"urn:btih:573cd607f880e8127ddccbf280bfe3a810606b5e","amp;dn":"American+Pie+2+%282001%29","amp;tr":["udp%3A%2F%2Ftracker.openbittorrent.com%3A80","udp%3A%2F%2Fopen.demonii.com%3A1337","udp%3A%2F%2Ftracker.coppersurfer.tk%3A6969","udp%3A%2F%2Fexodus.desync.com%3A6969"],"infoHash":"573cd607f880e8127ddccbf280bfe3a810606b5e","infoHashBuffer":{"type":"Buffer","data":[87,60,214,7,248,128,232,18,125,220,203,242,128,191,227,168,16,96,107,94]},"announce":[],"urlList":[]}}