{"title":"[Passion-HD] Jynx Maze (Morning Anal / 03.02.2015)","uid":11731396,"size":275291735,"categoryP":"porn","categoryS":"movies","magnet":"?xt=urn:btih:5da9142d9a701d17a9dc7a6ffff589f4c1bd4f33&amp;dn=%5BPassion-HD%5D+Jynx+Maze+%28Morning+Anal+%2F+03.02.2015%29&amp;tr=udp%3A%2F%2Ftracker.openbittorrent.com%3A80&amp;tr=udp%3A%2F%2Fopen.demonii.com%3A1337&amp;tr=udp%3A%2F%2Ftracker.coppersurfer.tk%3A6969&amp;tr=udp%3A%2F%2Fexodus.desync.com%3A6969","seeders":6,"leechers":11,"uploader":"chkm8te","files":1,"time":1425406745,"description":"[Passion-HD] Jynx Maze (Morning Anal / 03.02.2015)\n\n\nScreens: &lt;a href=&quot;\nhttp://xxxhost.me/viewer.php?file=1w6ab51lu5phq5ev9gj3.jpg&quot; rel=&quot;nofollow&quot; target=&quot;_NEW&quot;&gt;\nhttp://xxxhost.me/viewer.php?file=1w6ab51lu5phq5ev9gj3.jpg&lt;/a&gt;\n &lt;a href=&quot;\nhttp://xxxhost.me/viewer.php?file=brzihw95gjnepumlbncy.jpg&quot; rel=&quot;nofollow&quot; target=&quot;_NEW&quot;&gt;\nhttp://xxxhost.me/viewer.php?file=brzihw95gjnepumlbncy.jpg&lt;/a&gt;","torrent":{"xt":"urn:btih:5da9142d9a701d17a9dc7a6ffff589f4c1bd4f33","amp;dn":"%5BPassion-HD%5D+Jynx+Maze+%28Morning+Anal+%2F+03.02.2015%29","amp;tr":["udp%3A%2F%2Ftracker.openbittorrent.com%3A80","udp%3A%2F%2Fopen.demonii.com%3A1337","udp%3A%2F%2Ftracker.coppersurfer.tk%3A6969","udp%3A%2F%2Fexodus.desync.com%3A6969"],"infoHash":"5da9142d9a701d17a9dc7a6ffff589f4c1bd4f33","infoHashBuffer":{"type":"Buffer","data":[93,169,20,45,154,112,29,23,169,220,122,111,255,245,137,244,193,189,79,51]},"announce":[],"urlList":[]}}