{"title":"Never Let Go - Book by Dan John, epub","uid":8549699,"size":387900,"categoryP":"other","categoryS":"e_books","magnet":"?xt=urn:btih:6475d3036cad11b03435d109e51fcad97b6580b3&amp;dn=Never+Let+Go+-+Book+by+Dan+John%2C+epub&amp;tr=udp%3A%2F%2Ftracker.openbittorrent.com%3A80&amp;tr=udp%3A%2F%2Fopen.demonii.com%3A1337&amp;tr=udp%3A%2F%2Ftracker.coppersurfer.tk%3A6969&amp;tr=udp%3A%2F%2Fexodus.desync.com%3A6969","seeders":6,"leechers":0,"uploader":null,"files":1,"time":1370613902,"description":" &lt;a href=&quot;http://danjohn.net/2009/11/never-let-go/&quot; rel=&quot;nofollow&quot; target=&quot;_NEW&quot;&gt;http://danjohn.net/2009/11/never-let-go/&lt;/a&gt;","torrent":{"xt":"urn:btih:6475d3036cad11b03435d109e51fcad97b6580b3","amp;dn":"Never+Let+Go+-+Book+by+Dan+John%2C+epub","amp;tr":["udp%3A%2F%2Ftracker.openbittorrent.com%3A80","udp%3A%2F%2Fopen.demonii.com%3A1337","udp%3A%2F%2Ftracker.coppersurfer.tk%3A6969","udp%3A%2F%2Fexodus.desync.com%3A6969"],"infoHash":"6475d3036cad11b03435d109e51fcad97b6580b3","infoHashBuffer":{"type":"Buffer","data":[100,117,211,3,108,173,17,176,52,53,209,9,229,31,202,217,123,101,128,179]},"announce":[],"urlList":[]}}