{"title":"Poltergeist NL sub avi (MovieNight)","uid":6838655,"size":1019987372,"categoryP":"video","categoryS":"movies","magnet":"?xt=urn:btih:66185b7d82b0624b554df9ba9f8c5e9a28e056ab&amp;dn=Poltergeist+NL+sub+avi+%28MovieNight%29&amp;tr=udp%3A%2F%2Ftracker.openbittorrent.com%3A80&amp;tr=udp%3A%2F%2Fopen.demonii.com%3A1337&amp;tr=udp%3A%2F%2Ftracker.coppersurfer.tk%3A6969&amp;tr=udp%3A%2F%2Fexodus.desync.com%3A6969","seeders":6,"leechers":0,"uploader":"MovieNight","files":-1,"time":1322091805,"description":"Poltergeist (1982)\n\nVerenigde Staten\nHorror / Thriller\n114 minuten\n\ngeregisseerd door Steven Spielberg, Tobe Hooper\nmet Craig T. Nelson, Jobeth Williams en Heather O'Rourke\n\nHet rustige leven van de familie Feeling wordt verstoord door geesten. Op het eerste gezicht lijken de geesten vriendelijk te zijn: ze verplaatsen objecten als amusement voor het gezin. Maar dan worden ze gemeen en beginnen ze het gezin te terroriseren. Ze gaan zelfs zover dat ze hun dochter kidnappen. Haar vader roept de hulp in van klopgeest specialisten.\n\n\n\nMovieNight","torrent":{"xt":"urn:btih:66185b7d82b0624b554df9ba9f8c5e9a28e056ab","amp;dn":"Poltergeist+NL+sub+avi+%28MovieNight%29","amp;tr":["udp%3A%2F%2Ftracker.openbittorrent.com%3A80","udp%3A%2F%2Fopen.demonii.com%3A1337","udp%3A%2F%2Ftracker.coppersurfer.tk%3A6969","udp%3A%2F%2Fexodus.desync.com%3A6969"],"infoHash":"66185b7d82b0624b554df9ba9f8c5e9a28e056ab","infoHashBuffer":{"type":"Buffer","data":[102,24,91,125,130,176,98,75,85,77,249,186,159,140,94,154,40,224,86,171]},"announce":[],"urlList":[]}}