{"title":"Mary J. Blige - 1992 - What's The 411","uid":7503931,"size":128014354,"categoryP":"audio","categoryS":"music","magnet":"?xt=urn:btih:76c76f14f17452a7ae7a9c335d64e9d8de338803&amp;dn=Mary+J.+Blige+-+1992+-+What%27s+The+411&amp;tr=udp%3A%2F%2Ftracker.openbittorrent.com%3A80&amp;tr=udp%3A%2F%2Fopen.demonii.com%3A1337&amp;tr=udp%3A%2F%2Ftracker.coppersurfer.tk%3A6969&amp;tr=udp%3A%2F%2Fexodus.desync.com%3A6969","seeders":6,"leechers":0,"uploader":"minarcus","files":-1,"time":1344106167,"description":"1\tLeave a Message\n2\tReminisce\n3\tReal Love\n4\tYou Remind Me\n5\tIntro Talk\n6\tSweet Thing\n7\tLove No Limit\n8\tI Don't Want to Do Anything\n9\tSlow Down\n10\tMy Love\n11\tChanges I've Been Going Through\n12\tWhat's the 411?","torrent":{"xt":"urn:btih:76c76f14f17452a7ae7a9c335d64e9d8de338803","amp;dn":"Mary+J.+Blige+-+1992+-+What%27s+The+411","amp;tr":["udp%3A%2F%2Ftracker.openbittorrent.com%3A80","udp%3A%2F%2Fopen.demonii.com%3A1337","udp%3A%2F%2Ftracker.coppersurfer.tk%3A6969","udp%3A%2F%2Fexodus.desync.com%3A6969"],"infoHash":"76c76f14f17452a7ae7a9c335d64e9d8de338803","infoHashBuffer":{"type":"Buffer","data":[118,199,111,20,241,116,82,167,174,122,156,51,93,100,233,216,222,51,136,3]},"announce":[],"urlList":[]}}