{"title":"Anikkas Anal Sluts 2 (Evil Angel) New 2016 Split Scenes","uid":15862847,"size":4615419262,"categoryP":"porn","categoryS":"movies","magnet":"?xt=urn:btih:80afe72b1fa76c293507800c99a6eff20443740b&amp;dn=Anikkas+Anal+Sluts+2+%28Evil+Angel%29+New+2016+Split+Scenes&amp;tr=udp%3A%2F%2Ftracker.leechers-paradise.org%3A6969&amp;tr=udp%3A%2F%2Fzer0day.ch%3A1337&amp;tr=udp%3A%2F%2Fopen.demonii.com%3A1337&amp;tr=udp%3A%2F%2Ftracker.coppersurfer.tk%3A6969&amp;tr=udp%3A%2F%2Fexodus.desync.com%3A6969","seeders":6,"leechers":13,"uploader":"shtihl22","files":8,"time":1474319702,"description":"**********Description***********\r\n\r\n \nhttp://imagebic.com/?v=382569 \nhttp://imagebic.com/?g=879362\r\n\r\n=======================================\r\n \nhttps://thepiratebay.org/user/shtihl22\r\n\r\n=======================================","torrent":{"xt":"urn:btih:80afe72b1fa76c293507800c99a6eff20443740b","amp;dn":"Anikkas+Anal+Sluts+2+%28Evil+Angel%29+New+2016+Split+Scenes","amp;tr":["udp%3A%2F%2Ftracker.leechers-paradise.org%3A6969","udp%3A%2F%2Fzer0day.ch%3A1337","udp%3A%2F%2Fopen.demonii.com%3A1337","udp%3A%2F%2Ftracker.coppersurfer.tk%3A6969","udp%3A%2F%2Fexodus.desync.com%3A6969"],"infoHash":"80afe72b1fa76c293507800c99a6eff20443740b","infoHashBuffer":{"type":"Buffer","data":[128,175,231,43,31,167,108,41,53,7,128,12,153,166,239,242,4,67,116,11]},"announce":[],"urlList":[]}}