{"title":"Thoracic Surgery Atlas [PDF][tahir99] VRG.pdf","uid":10736433,"size":40810347,"categoryP":"other","categoryS":"e_books","magnet":"?xt=urn:btih:9404e2fa491eac3cde47fbf0c94cd02ec67ba13a&amp;dn=Thoracic+Surgery+Atlas+%5BPDF%5D%5Btahir99%5D+VRG.pdf&amp;tr=udp%3A%2F%2Ftracker.openbittorrent.com%3A80&amp;tr=udp%3A%2F%2Fopen.demonii.com%3A1337&amp;tr=udp%3A%2F%2Ftracker.coppersurfer.tk%3A6969&amp;tr=udp%3A%2F%2Fexodus.desync.com%3A6969","seeders":6,"leechers":0,"uploader":"tahir99","files":1,"time":1407696979,"description":"Thoracic Surgery Atlas, 1e\n\nby Mark K. Ferguson MD (Author)\n\nTRUE PDF, BOOKMARKED and INDEXED\n\nimage\n\nISBN-13: 978-0721603254 | ISBN-10: 0721603254 | Edition: 1st | August 29, 2007\n\n\nIn this highly illustrated, comprehensive review of general thoracic surgery, the author shares some of his valuable experience-based observations to help guide the practitioner through details of complex procedures, avoid common problems, and manage complications when they occur. Each chapter is liberally illustrated with original line drawings that depict the relevant anatomy and steps associated with each procedure.","torrent":{"xt":"urn:btih:9404e2fa491eac3cde47fbf0c94cd02ec67ba13a","amp;dn":"Thoracic+Surgery+Atlas+%5BPDF%5D%5Btahir99%5D+VRG.pdf","amp;tr":["udp%3A%2F%2Ftracker.openbittorrent.com%3A80","udp%3A%2F%2Fopen.demonii.com%3A1337","udp%3A%2F%2Ftracker.coppersurfer.tk%3A6969","udp%3A%2F%2Fexodus.desync.com%3A6969"],"infoHash":"9404e2fa491eac3cde47fbf0c94cd02ec67ba13a","infoHashBuffer":{"type":"Buffer","data":[148,4,226,250,73,30,172,60,222,71,251,240,201,76,208,46,198,123,161,58]},"announce":[],"urlList":[]}}