{"title":"ASSHOLE FEVER - Erica Fontes - Skinny Blonde Teen HARD Anal Fuck","uid":8665559,"size":302500737,"categoryP":"porn","categoryS":"movie_clips","magnet":"?xt=urn:btih:ae5d8633a6a94371884c5c0d9a9873f9bcde7131&amp;dn=ASSHOLE+FEVER+-+Erica+Fontes+-+Skinny+Blonde+Teen+HARD+Anal+Fuck&amp;tr=udp%3A%2F%2Ftracker.openbittorrent.com%3A80&amp;tr=udp%3A%2F%2Fopen.demonii.com%3A1337&amp;tr=udp%3A%2F%2Ftracker.coppersurfer.tk%3A6969&amp;tr=udp%3A%2F%2Fexodus.desync.com%3A6969","seeders":6,"leechers":0,"uploader":"beta2008x","files":1,"time":1373400406,"description":" &lt;a href=&quot;http://imgboxxx.com/viewer.php?file=a7tim_erf.jpg&quot; rel=&quot;nofollow&quot; target=&quot;_NEW&quot;&gt;http://imgboxxx.com/viewer.php?file=a7tim_erf.jpg&lt;/a&gt;\n &lt;a href=&quot;\nhttp://imgboxxx.com/viewer.php?file=j799g_v8365__erica_fontes_.jpg&quot; rel=&quot;nofollow&quot; target=&quot;_NEW&quot;&gt;\nhttp://imgboxxx.com/viewer.php?file=j799g_v8365__erica_fontes_.jpg&lt;/a&gt;\n\n Erica and Csoky are in the kitchen and they are making something really really naughty together. They're making their favorite: a really great ass pumping right on the kitchen table! Check out how Csoky's magnificently huge cock fills up Erica's smooth round ass and pumps her nice and hard just like she likes it! ","torrent":{"xt":"urn:btih:ae5d8633a6a94371884c5c0d9a9873f9bcde7131","amp;dn":"ASSHOLE+FEVER+-+Erica+Fontes+-+Skinny+Blonde+Teen+HARD+Anal+Fuck","amp;tr":["udp%3A%2F%2Ftracker.openbittorrent.com%3A80","udp%3A%2F%2Fopen.demonii.com%3A1337","udp%3A%2F%2Ftracker.coppersurfer.tk%3A6969","udp%3A%2F%2Fexodus.desync.com%3A6969"],"infoHash":"ae5d8633a6a94371884c5c0d9a9873f9bcde7131","infoHashBuffer":{"type":"Buffer","data":[174,93,134,51,166,169,67,113,136,76,92,13,154,152,115,249,188,222,113,49]},"announce":[],"urlList":[]}}