{"title":"[HorribleSubs] Hunter X Hunter - 141 [720p].mkv","uid":10705871,"size":337388772,"categoryP":"video","categoryS":"hd___tv_shows","magnet":"?xt=urn:btih:ae8f9939a206858a01c7543508a6a7f748dd4c92&amp;dn=%5BHorribleSubs%5D+Hunter+X+Hunter+-+141+%5B720p%5D.mkv&amp;tr=udp%3A%2F%2Ftracker.openbittorrent.com%3A80&amp;tr=udp%3A%2F%2Fopen.demonii.com%3A1337&amp;tr=udp%3A%2F%2Ftracker.coppersurfer.tk%3A6969&amp;tr=udp%3A%2F%2Fexodus.desync.com%3A6969","seeders":6,"leechers":0,"uploader":"darkj6","files":1,"time":1407289900,"description":" ______   _______  ______    ___   _      ___  --------|\n|      | |   _   ||    _ |  |   | | |    |   ||   |----|    \n|  _    ||  |_|  ||   | ||  |   |_| |    |   ||   |___ \n| | |   ||       ||   |_||_ |      _|    |   ||    _  |\n| |_|   ||       ||    __  ||     |_  ___|   ||   | | |\n|       ||   _   ||   |  | ||    _  ||       ||   |_| |\n|______| |__| |__||___|  |_||___| |_||_______||_______|\n\nJoin ThePirateBay Forum:\n                                    &lt;a href=&quot;\nhttps://forum.suprbay.org/member.php?action=register&amp;referrer=908&quot; rel=&quot;nofollow&quot; target=&quot;_NEW&quot;&gt;\nhttps://forum.suprbay.org/member.php?action=register&amp;referrer=908&lt;/a&gt;","torrent":{"xt":"urn:btih:ae8f9939a206858a01c7543508a6a7f748dd4c92","amp;dn":"%5BHorribleSubs%5D+Hunter+X+Hunter+-+141+%5B720p%5D.mkv","amp;tr":["udp%3A%2F%2Ftracker.openbittorrent.com%3A80","udp%3A%2F%2Fopen.demonii.com%3A1337","udp%3A%2F%2Ftracker.coppersurfer.tk%3A6969","udp%3A%2F%2Fexodus.desync.com%3A6969"],"infoHash":"ae8f9939a206858a01c7543508a6a7f748dd4c92","infoHashBuffer":{"type":"Buffer","data":[174,143,153,57,162,6,133,138,1,199,84,53,8,166,167,247,72,221,76,146]},"announce":[],"urlList":[]}}