{"title":"Chris Carmichael's Food for Fitness ","uid":10710307,"size":4928591,"categoryP":"other","categoryS":"e_books","magnet":"?xt=urn:btih:b29c2d907f335111dbe3b80c2a278e314d84bcf9&amp;dn=Chris+Carmichael%27s+Food+for+Fitness+&amp;tr=udp%3A%2F%2Ftracker.openbittorrent.com%3A80&amp;tr=udp%3A%2F%2Fopen.demonii.com%3A1337&amp;tr=udp%3A%2F%2Ftracker.coppersurfer.tk%3A6969&amp;tr=udp%3A%2F%2Fexodus.desync.com%3A6969","seeders":6,"leechers":0,"uploader":"mdusanjay","files":-1,"time":1407345426,"description":"Chris Carmichael's Food for Fitness by Chris Carmichael, Jim Rutberg, Kathy Zawadzki\n\nEnglish | 2005 | ISBN: 0425202550 | 448 pages | EPUB | 4,7 MB\n\n\nFrom the coach of Lance Armstrong and several more of the world's greatest athletes comes a revolutionary eating plan for all active people - from weekend warriors to elite competitors to those just trying to lose a few pounds and be more fit.","torrent":{"xt":"urn:btih:b29c2d907f335111dbe3b80c2a278e314d84bcf9","amp;dn":"Chris+Carmichael%27s+Food+for+Fitness+","amp;tr":["udp%3A%2F%2Ftracker.openbittorrent.com%3A80","udp%3A%2F%2Fopen.demonii.com%3A1337","udp%3A%2F%2Ftracker.coppersurfer.tk%3A6969","udp%3A%2F%2Fexodus.desync.com%3A6969"],"infoHash":"b29c2d907f335111dbe3b80c2a278e314d84bcf9","infoHashBuffer":{"type":"Buffer","data":[178,156,45,144,127,51,81,17,219,227,184,12,42,39,142,49,77,132,188,249]},"announce":[],"urlList":[]}}