{"title":"Teen Fidelity - Karla Kush - Opposites Attract ** Mar 21, 2014 N","uid":9811291,"size":770764920,"categoryP":"porn","categoryS":"movie_clips","magnet":"?xt=urn:btih:b7835dde540e470f64420e9cae83486a08659b3b&amp;dn=Teen+Fidelity+-+Karla+Kush+-+Opposites+Attract+%2A%2A+Mar+21%2C+2014+N&amp;tr=udp%3A%2F%2Ftracker.openbittorrent.com%3A80&amp;tr=udp%3A%2F%2Fopen.demonii.com%3A1337&amp;tr=udp%3A%2F%2Ftracker.coppersurfer.tk%3A6969&amp;tr=udp%3A%2F%2Fexodus.desync.com%3A6969","seeders":6,"leechers":1,"uploader":"nwpornup","files":1,"time":1395532567,"description":" &lt;a href=&quot;http://imgfun.biz/img-532e13c3b9e33.html&quot; rel=&quot;nofollow&quot; target=&quot;_NEW&quot;&gt;http://imgfun.biz/img-532e13c3b9e33.html&lt;/a&gt;\n","torrent":{"xt":"urn:btih:b7835dde540e470f64420e9cae83486a08659b3b","amp;dn":"Teen+Fidelity+-+Karla+Kush+-+Opposites+Attract+%2A%2A+Mar+21%2C+2014+N","amp;tr":["udp%3A%2F%2Ftracker.openbittorrent.com%3A80","udp%3A%2F%2Fopen.demonii.com%3A1337","udp%3A%2F%2Ftracker.coppersurfer.tk%3A6969","udp%3A%2F%2Fexodus.desync.com%3A6969"],"infoHash":"b7835dde540e470f64420e9cae83486a08659b3b","infoHashBuffer":{"type":"Buffer","data":[183,131,93,222,84,14,71,15,100,66,14,156,174,131,72,106,8,101,155,59]},"announce":[],"urlList":[]}}