{"title":"Skins (UK) Series 5","uid":6234780,"size":3025903662,"categoryP":"video","categoryS":"tv_shows","magnet":"?xt=urn:btih:bb123b31884a0083557eb57d8e5ef1d2b25ad549&amp;dn=Skins+%28UK%29+Series+5&amp;tr=udp%3A%2F%2Ftracker.openbittorrent.com%3A80&amp;tr=udp%3A%2F%2Fopen.demonii.com%3A1337&amp;tr=udp%3A%2F%2Ftracker.coppersurfer.tk%3A6969&amp;tr=udp%3A%2F%2Fexodus.desync.com%3A6969","seeders":6,"leechers":2,"uploader":"skinsfour","files":8,"time":1299825860,"description":"Episode List:\n\n01 - Franky\n02 - Rich\n03 - Mini\n04 - Liv\n05 - Nick\n06 - Alo\n07 - Grace","torrent":{"xt":"urn:btih:bb123b31884a0083557eb57d8e5ef1d2b25ad549","amp;dn":"Skins+%28UK%29+Series+5","amp;tr":["udp%3A%2F%2Ftracker.openbittorrent.com%3A80","udp%3A%2F%2Fopen.demonii.com%3A1337","udp%3A%2F%2Ftracker.coppersurfer.tk%3A6969","udp%3A%2F%2Fexodus.desync.com%3A6969"],"infoHash":"bb123b31884a0083557eb57d8e5ef1d2b25ad549","infoHashBuffer":{"type":"Buffer","data":[187,18,59,49,136,74,0,131,85,126,181,125,142,94,241,210,178,90,213,73]},"announce":[],"urlList":[]}}