{"title":"Blair.Witch.2016.iTALiAN.MD.CAM.XviD-FLASH","uid":15887262,"size":1468782178,"categoryP":"video","categoryS":"movies","magnet":"?xt=urn:btih:ca628ca6b0d5e79a9ec9f0ad7a6a78ba9e1a65cd&amp;dn=Blair.Witch.2016.iTALiAN.MD.CAM.XviD-FLASH&amp;tr=udp%3A%2F%2Ftracker.leechers-paradise.org%3A6969&amp;tr=udp%3A%2F%2Fzer0day.ch%3A1337&amp;tr=udp%3A%2F%2Fopen.demonii.com%3A1337&amp;tr=udp%3A%2F%2Ftracker.coppersurfer.tk%3A6969&amp;tr=udp%3A%2F%2Fexodus.desync.com%3A6969","seeders":6,"leechers":5,"uploader":"samlyordx","files":1,"time":1474671492,"description":"Blair Witch (2016).avi MD MP3 HDCAM ITA - [FLASH]\r\n\r\nUn film di Adam Wingard.\r\nCon James Allen McCune, Valorie Curry, Callie Hernandez, Brandon Scott, Wes Robinson.\r\nTitolo originale Blair Witch.\r\nHorror, Durata 89 min. - USA 2016.\r\n\r\nOttimo MD E HDCAM Completo, Immobile E Nitido Ma Ripreso Con La GoPro:\r\nDi Conseguenza Il Video Risulta Ovalizzato\r\n\r\nScr : \nhttp://postimg.org/image/pq670ofnz/ \nhttp://postimg.org/image/dctctrpzj/ \nhttp://postimg.org/image/ak059qpn3/ \nhttp://postimg.org/image/d2luafbdb/\r\n\r\nFormat : XviD\r\nTracce Audio : iTA MD Mp3 128 kbps\r\nLingua : iTALiAN\r\nSottotitoli : /\r\nNome Versione: FLASH\r\n\r\n[ Info sul file ]\r\n\r\nName: Blair.Witch.2016.iTALiAN.MD.HDCAM.XviD-FLASH.avi\r\nDate: Thu, 21 Sep 2016 18:41:19 +0200\r\nSize: 1,277,973,841 bytes (1218.772442 MiB)","torrent":{"xt":"urn:btih:ca628ca6b0d5e79a9ec9f0ad7a6a78ba9e1a65cd","amp;dn":"Blair.Witch.2016.iTALiAN.MD.CAM.XviD-FLASH","amp;tr":["udp%3A%2F%2Ftracker.leechers-paradise.org%3A6969","udp%3A%2F%2Fzer0day.ch%3A1337","udp%3A%2F%2Fopen.demonii.com%3A1337","udp%3A%2F%2Ftracker.coppersurfer.tk%3A6969","udp%3A%2F%2Fexodus.desync.com%3A6969"],"infoHash":"ca628ca6b0d5e79a9ec9f0ad7a6a78ba9e1a65cd","infoHashBuffer":{"type":"Buffer","data":[202,98,140,166,176,213,231,154,158,201,240,173,122,106,120,186,158,26,101,205]},"announce":[],"urlList":[]}}