{"title":"Cold-Year_Of_The_Spider_(Retail)-2003-HHI","uid":6246225,"size":95002717,"categoryP":"audio","categoryS":"music","magnet":"?xt=urn:btih:d865cefc4e6c25bc5737c6b1822fdc84c50ab404&amp;dn=Cold-Year_Of_The_Spider_%28Retail%29-2003-HHI&amp;tr=udp%3A%2F%2Ftracker.openbittorrent.com%3A80&amp;tr=udp%3A%2F%2Fopen.demonii.com%3A1337&amp;tr=udp%3A%2F%2Ftracker.coppersurfer.tk%3A6969&amp;tr=udp%3A%2F%2Fexodus.desync.com%3A6969","seeders":6,"leechers":0,"uploader":"raidy","files":16,"time":1300240689,"description":"Artist: Cold \n Album: Year of the spider \n Grabber : EAC \n Encoder : LAME v3.90.3 \n Release Date: May-13-2003 \n Rip Date....: Feb-08-2004 \n Genre.......: Alternrock \n Quality : VBRkbps / 44.1kHz / Joint-Stereo \n Playtime : 63:58 min \n Ripper : Happy Hacker Industries \n Supplier : HHI \n CD Songs : 13 \n\nTrack Listing....: \n 01.Remedy [02:58] \n 02.Suffocate [03:40] \n 03.Cure my tragedy [03:55] \n (A letter to god) \n 04.Stupid girl [03:10] \n 05.Don't belong [03:40] \n 06.Wasted years [04:07] \n 07.Whatever you became [03:45] \n 08.Sad happy [03:36] \n 09.Rain song [03:38] \n 10.The day seattle died [03:34] \n 11.Change the world [04:01] \n 12.Black sunday [04:31] \n 13.Kill the music industry [19:23] \n ____ \n \n 63:58 min \n 90,6 MB","torrent":{"xt":"urn:btih:d865cefc4e6c25bc5737c6b1822fdc84c50ab404","amp;dn":"Cold-Year_Of_The_Spider_%28Retail%29-2003-HHI","amp;tr":["udp%3A%2F%2Ftracker.openbittorrent.com%3A80","udp%3A%2F%2Fopen.demonii.com%3A1337","udp%3A%2F%2Ftracker.coppersurfer.tk%3A6969","udp%3A%2F%2Fexodus.desync.com%3A6969"],"infoHash":"d865cefc4e6c25bc5737c6b1822fdc84c50ab404","infoHashBuffer":{"type":"Buffer","data":[216,101,206,252,78,108,37,188,87,55,198,177,130,47,220,132,197,10,180,4]},"announce":[],"urlList":[]}}