{"title":"Blacked - Kylie Page - Girlfriend Cheats On Fiance With BBC","uid":15518653,"size":281128056,"categoryP":"porn","categoryS":"movie_clips","magnet":"?xt=urn:btih:de06592442963d27f3788f2bc5a4e230a2c9733d&amp;dn=Blacked+-+Kylie+Page+-+Girlfriend+Cheats+On+Fiance+With+BBC&amp;tr=udp%3A%2F%2Ftracker.leechers-paradise.org%3A6969&amp;tr=udp%3A%2F%2Fzer0day.ch%3A1337&amp;tr=udp%3A%2F%2Fopen.demonii.com%3A1337&amp;tr=udp%3A%2F%2Ftracker.coppersurfer.tk%3A6969&amp;tr=udp%3A%2F%2Fexodus.desync.com%3A6969","seeders":6,"leechers":1,"uploader":"gemini527nj","files":1,"time":1470715970,"description":"Blacked - Kylie Page - Girlfriend Cheats On Fiance With BBC (480p_1000)\r\n\r\nScreenshots:\r\n------------ \nhttp://xxxhost.me/viewer.php?file=dy19zjxori73erkw663j.jpeg\r\n \nhttp://xxxhost.me/viewer.php?file=e4dstbcntl8tx85ajwov.jpg","torrent":{"xt":"urn:btih:de06592442963d27f3788f2bc5a4e230a2c9733d","amp;dn":"Blacked+-+Kylie+Page+-+Girlfriend+Cheats+On+Fiance+With+BBC","amp;tr":["udp%3A%2F%2Ftracker.leechers-paradise.org%3A6969","udp%3A%2F%2Fzer0day.ch%3A1337","udp%3A%2F%2Fopen.demonii.com%3A1337","udp%3A%2F%2Ftracker.coppersurfer.tk%3A6969","udp%3A%2F%2Fexodus.desync.com%3A6969"],"infoHash":"de06592442963d27f3788f2bc5a4e230a2c9733d","infoHashBuffer":{"type":"Buffer","data":[222,6,89,36,66,150,61,39,243,120,143,43,197,164,226,48,162,201,115,61]},"announce":[],"urlList":[]}}